{
  "themes": [
    {
      "name": "Dark+ (default)",
      "id": "dark-plus",
      "type": "dark",
      "colors": {
        "editor.background": "#1e1e1e",
        "editor.foreground": "#d4d4d4",
        "editorLineNumber.foreground": "#858585",
        "editorLineNumber.activeForeground": "#c6c6c6",
        "editorCursor.foreground": "#d7d7d7",
        "editorWhitespace.foreground": "#3b3b3b",
        "editor.selectionBackground": "#264f78",
        "editor.inactiveSelectionBackground": "#3a3d41",
        "editor.selectionHighlightBackground": "#add6ff26",
        "editor.findMatchBackground": "#515c6a",
        "editor.findMatchHighlightBackground": "#ea5c0055",
        "editor.wordHighlightBackground": "#575757b8",
        "editor.wordHighlightStrongBackground": "#004972b8",
        "editor.lineHighlightBackground": "#ffffff10",
        "editorLink.activeForeground": "#4e94ce",
        "editorIndentGuide.background": "#404040",
        "editorIndentGuide.activeBackground": "#707070",
        "editorRuler.foreground": "#5a5a5a",
        "editorBracketMatch.background": "#0064001a",
        "editorBracketMatch.border": "#888888",
        
        "activityBar.background": "#1f1f1f",
        "activityBar.foreground": "#d7d7d7",
        "activityBar.inactiveForeground": "#ffffff66",
        "activityBarBadge.background": "#007acc",
        "activityBarBadge.foreground": "#ffffff",
        
        "sideBar.background": "#252526",
        "sideBar.foreground": "#cccccc",
        "sideBarTitle.foreground": "#bbbbbb",
        "sideBarSectionHeader.background": "#00000000",
        "sideBarSectionHeader.foreground": "#cccccc",
        
        "list.activeSelectionBackground": "#094771",
        "list.activeSelectionForeground": "#ffffff",
        "list.inactiveSelectionBackground": "#37373d",
        "list.inactiveSelectionForeground": "#cccccc",
        "list.hoverBackground": "#2a2d2e",
        "list.hoverForeground": "#cccccc",
        
        "statusBar.background": "#007acc",
        "statusBar.foreground": "#ffffff",
        "statusBar.debuggingBackground": "#cc6633",
        "statusBar.debuggingForeground": "#ffffff",
        "statusBar.noFolderBackground": "#68217a",
        "statusBar.noFolderForeground": "#ffffff",
        
        "terminal.background": "#1e1e1e",
        "terminal.foreground": "#cccccc",
        "terminal.ansiBlack": "#000000",
        "terminal.ansiBlue": "#2472c8",
        "terminal.ansiBrightBlack": "#666666",
        "terminal.ansiBrightBlue": "#3b8eea",
        "terminal.ansiBrightCyan": "#29b8db",
        "terminal.ansiBrightGreen": "#23d18b",
        "terminal.ansiBrightMagenta": "#d670d6",
        "terminal.ansiBrightRed": "#f14c4c",
        "terminal.ansiBrightWhite": "#e5e5e5",
        "terminal.ansiBrightYellow": "#f5f543",
        "terminal.ansiCyan": "#11a8cd",
        "terminal.ansiGreen": "#0dbc79",
        "terminal.ansiMagenta": "#bc3fbc",
        "terminal.ansiRed": "#cd3131",
        "terminal.ansiWhite": "#e5e5e5",
        "terminal.ansiYellow": "#e5e510",
        
        "titleBar.activeBackground": "#3c3c3c",
        "titleBar.activeForeground": "#cccccc",
        "titleBar.inactiveBackground": "#3c3c3c99",
        "titleBar.inactiveForeground": "#cccccc99"
      }
    },
    {
      "name": "Light+ (default light)",
      "id": "light-plus",
      "type": "light",
      "colors": {
        "editor.background": "#ffffff",
        "editor.foreground": "#000000",
        "editorLineNumber.foreground": "#237893",
        "editorLineNumber.activeForeground": "#0b216f",
        "editorCursor.foreground": "#000000",
        "editorWhitespace.foreground": "#bfbfbf",
        "editor.selectionBackground": "#add6ff",
        "editor.inactiveSelectionBackground": "#e5ebf1",
        "editor.selectionHighlightBackground": "#add6ff80",
        "editor.findMatchBackground": "#a8ac94",
        "editor.findMatchHighlightBackground": "#f8c9ab",
        "editor.lineHighlightBackground": "#f3f3f3",
        "editorLink.activeForeground": "#0000ff",
        "editorIndentGuide.background": "#d3d3d3",
        "editorIndentGuide.activeBackground": "#939393",
        "editorRuler.foreground": "#d3d3d3",
        "editorBracketMatch.background": "#0064001a",
        "editorBracketMatch.border": "#b9b9b9",
        
        "activityBar.background": "#f3f3f3",
        "activityBar.foreground": "#333333",
        "activityBar.inactiveForeground": "#33333399",
        "activityBarBadge.background": "#007acc",
        "activityBarBadge.foreground": "#ffffff",
        
        "sideBar.background": "#f3f3f3",
        "sideBar.foreground": "#333333",
        "sideBarTitle.foreground": "#6f6f6f",
        "sideBarSectionHeader.background": "#00000000",
        "sideBarSectionHeader.foreground": "#333333",
        
        "list.activeSelectionBackground": "#0060c0",
        "list.activeSelectionForeground": "#ffffff",
        "list.inactiveSelectionBackground": "#e4e6f1",
        "list.inactiveSelectionForeground": "#333333",
        "list.hoverBackground": "#e8e8e8",
        "list.hoverForeground": "#333333",
        
        "statusBar.background": "#007acc",
        "statusBar.foreground": "#ffffff",
        "statusBar.debuggingBackground": "#cc6633",
        "statusBar.debuggingForeground": "#ffffff",
        "statusBar.noFolderBackground": "#68217a",
        "statusBar.noFolderForeground": "#ffffff",
        
        "terminal.background": "#ffffff",
        "terminal.foreground": "#333333",
        "terminal.ansiBlack": "#000000",
        "terminal.ansiBlue": "#0451a5",
        "terminal.ansiBrightBlack": "#666666",
        "terminal.ansiBrightBlue": "#0451a5",
        "terminal.ansiBrightCyan": "#0598bc",
        "terminal.ansiBrightGreen": "#14ce14",
        "terminal.ansiBrightMagenta": "#bc05bc",
        "terminal.ansiBrightRed": "#cd3131",
        "terminal.ansiBrightWhite": "#a5a5a5",
        "terminal.ansiBrightYellow": "#b5ba00",
        "terminal.ansiCyan": "#0598bc",
        "terminal.ansiGreen": "#00bc00",
        "terminal.ansiMagenta": "#bc05bc",
        "terminal.ansiRed": "#cd3131",
        "terminal.ansiWhite": "#555555",
        "terminal.ansiYellow": "#949800",
        
        "titleBar.activeBackground": "#dddddd",
        "titleBar.activeForeground": "#333333",
        "titleBar.inactiveBackground": "#dddddd99",
        "titleBar.inactiveForeground": "#33333399"
      }
    },
    {
      "name": "High Contrast",
      "id": "high-contrast",
      "type": "hc",
      "colors": {
        "editor.background": "#000000",
        "editor.foreground": "#ffffff",
        "editorLineNumber.foreground": "#ffff00",
        "editorLineNumber.activeForeground": "#ffff00",
        "editorCursor.foreground": "#ffffff",
        "editorWhitespace.foreground": "#ffffff",
        "editor.selectionBackground": "#ffffff",
        "editor.selectionForeground": "#000000",
        "editor.inactiveSelectionBackground": "#ffffff44",
        "editor.selectionHighlightBackground": "#ffffff44",
        "editor.findMatchBackground": "#00000000",
        "editor.findMatchBorder": "#ffff00",
        "editor.findMatchHighlightBackground": "#00000000",
        "editor.findMatchHighlightBorder": "#ffff00",
        "editor.lineHighlightBackground": "#ffffff1f",
        "editorLink.activeForeground": "#ffff00",
        "editorIndentGuide.background": "#ffffff50",
        "editorIndentGuide.activeBackground": "#ffffff",
        "editorRuler.foreground": "#ffffff",
        "editorBracketMatch.background": "#0000ff3d",
        "editorBracketMatch.border": "#ffff00",
        
        "activityBar.background": "#000000",
        "activityBar.foreground": "#ffffff",
        "activityBar.inactiveForeground": "#ffffff80",
        "activityBarBadge.background": "#ffff00",
        "activityBarBadge.foreground": "#000000",
        
        "sideBar.background": "#000000",
        "sideBar.foreground": "#ffffff",
        "sideBarTitle.foreground": "#ffffff",
        "sideBarSectionHeader.background": "#00000000",
        "sideBarSectionHeader.foreground": "#ffffff",
        
        "list.activeSelectionBackground": "#ffff00",
        "list.activeSelectionForeground": "#000000",
        "list.inactiveSelectionBackground": "#ffffff44",
        "list.inactiveSelectionForeground": "#ffffff",
        "list.hoverBackground": "#0000ff3d",
        "list.hoverForeground": "#ffffff",
        
        "statusBar.background": "#0000ff",
        "statusBar.foreground": "#ffffff",
        "statusBar.debuggingBackground": "#ff0000",
        "statusBar.debuggingForeground": "#ffffff",
        "statusBar.noFolderBackground": "#0000ff",
        "statusBar.noFolderForeground": "#ffffff",
        
        "terminal.background": "#000000",
        "terminal.foreground": "#ffffff",
        "terminal.ansiBlack": "#000000",
        "terminal.ansiBlue": "#0000ff",
        "terminal.ansiBrightBlack": "#666666",
        "terminal.ansiBrightBlue": "#0000ff",
        "terminal.ansiBrightCyan": "#00ffff",
        "terminal.ansiBrightGreen": "#00ff00",
        "terminal.ansiBrightMagenta": "#ff00ff",
        "terminal.ansiBrightRed": "#ff0000",
        "terminal.ansiBrightWhite": "#ffffff",
        "terminal.ansiBrightYellow": "#ffff00",
        "terminal.ansiCyan": "#00ffff",
        "terminal.ansiGreen": "#00ff00",
        "terminal.ansiMagenta": "#ff00ff",
        "terminal.ansiRed": "#ff0000",
        "terminal.ansiWhite": "#ffffff",
        "terminal.ansiYellow": "#ffff00",
        
        "titleBar.activeBackground": "#000000",
        "titleBar.activeForeground": "#ffffff",
        "titleBar.inactiveBackground": "#000000",
        "titleBar.inactiveForeground": "#ffffff80"
      }
    }
  ]
} 